{
  "images": [
    {
      "id": "1",
      "name": "A web designer",
      "url": "public/images/img1.jpg",
      "description": "A web designer in his office"
    },
    {
      "id": "2",
      "name": "A vacation",
      "url": "public/images/img2.jpg",
      "description": "A vacation in a Hawaiian island"
    },
    {
      "id": "3",
      "name": "A beautiful site",
      "url": "public/images/img3.jpg",
      "description": "A beautiful site with a lot of features"
    },
    {
      "id": "4",
      "name": "Picture of Fiona",
      "url": "public/images/img4.jpg",
      "description": "A picture of Fiona"
    },
    {
      "id": "5",
      "title": "Cool Pineapple",
      "url": "public/images/img5.jpg",
      "description": "A cool pineapple with shades"
    },
    {
      "id": "6",
      "name": "Caroline on a car",
      "url": "public/images/img6.jpg",
      "description": "Her modelling on a car"
    },
    {
      "id": "7",
      "name": "Modelling picture",
      "url": "public/images/img7.jpg",
      "description": "Her modelling in a studio"
    },
    {
      "id": "8",
      "name": "A web Developer",
      "url": "public/images/img8.jpg",
      "description": "A web developer in his office"
    },
    {
      "id": "8670",
      "name": "Smiley",
      "url": "https://encrypted-tbn0.gstatic.com/images?q=tbn:ANd9GcRRQzlBJZl-G-Za7N67rELie-QQZx64DJYi-w&s",
      "description": "Him smiling at you"
    }
  ]
}